deeplens/__init__.py
deeplens/extractor.py
deeplens/intervene.py
deeplens/pipeline.py
deeplens/sae.py
deeplens/train.py
deeplens/utils/__init__.py
deeplens/utils/analysis.py
deeplens/utils/dataset.py
deeplens/utils/tools.py
deeplens_sae-0.1.0.dist-info/licenses/LICENSE
deeplens_sae-0.1.0.dist-info/METADATA
deeplens_sae-0.1.0.dist-info/WHEEL
deeplens_sae-0.1.0.dist-info/top_level.txt
deeplens_sae-0.1.0.dist-info/RECORD
