Metadata-Version: 2.4
Name: deeplens-sae
Version: 0.1.0
Summary: A library to train and use Sparse Autoencoders for mechanistic interpretability
Author-email: Iñigo Parra <iparra@berkeley.edu>
License-Expression: MIT
Project-URL: Homepage, https://iparramartin.github.io/deeplens/
Project-URL: Documentation, https://iparramartin.github.io/deeplens/
Project-URL: Repository, https://github.com/iparramartin/deeplens
Project-URL: Bug Tracker, https://github.com/iparramartin/deeplens/issues
Keywords: machine-learning,interpretability,sparse-autoencoders,mechanistic-interpretability,deep-learning
Classifier: Development Status :: 3 - Alpha
Classifier: Intended Audience :: Developers
Classifier: Intended Audience :: Science/Research
Classifier: Topic :: Scientific/Engineering :: Artificial Intelligence
Classifier: Programming Language :: Python :: 3
Classifier: Programming Language :: Python :: 3.11
Classifier: Programming Language :: Python :: 3.12
Requires-Python: >=3.11
License-File: LICENSE
Requires-Dist: matplotlib==3.10.8
Requires-Dist: numpy<2
Requires-Dist: pandas==2.3.3
Requires-Dist: PyYAML==6.0.3
Requires-Dist: tqdm==4.67.1
Requires-Dist: transformers>=4.57.1
Requires-Dist: datasets==4.4.2
Requires-Dist: wandb==0.23.1
Dynamic: license-file
